vents/__init__.py
vents/config.py
vents/exceptions.py
vents/pkg.py
vents/settings.py
vents/connections/__init__.py
vents/connections/catalog.py
vents/connections/connection.py
vents/connections/connection_resource.py
vents/connections/connection_schema.py
vents/notifiers/__init__.py
vents/notifiers/base.py
vents/notifiers/discord_webhook.py
vents/notifiers/hipchat_webhook.py
vents/notifiers/mattermost_webhook.py
vents/notifiers/pagerduty_webhook.py
vents/notifiers/slack_webhook.py
vents/notifiers/spec.py
vents/notifiers/webhook.py
vents/providers/__init__.py
vents/providers/base.py
vents/providers/kinds.py
vents/providers/anthropic/__init__.py
vents/providers/anthropic/service.py
vents/providers/aws/__init__.py
vents/providers/aws/base.py
vents/providers/aws/s3.py
vents/providers/aws/service.py
vents/providers/azure/__init__.py
vents/providers/azure/base.py
vents/providers/azure/blob_storage.py
vents/providers/azure/service.py
vents/providers/gcp/__init__.py
vents/providers/gcp/base.py
vents/providers/gcp/gcs.py
vents/providers/gcp/service.py
vents/providers/github/__init__.py
vents/providers/github/service.py
vents/providers/openai/__init__.py
vents/providers/openai/service.py
vents/providers/reddit/__init__.py
vents/providers/reddit/service.py
vents/providers/slack/__init__.py
vents/providers/slack/service.py
vents-0.7.0.dist-info/LICENSE
vents-0.7.0.dist-info/METADATA
vents-0.7.0.dist-info/WHEEL
vents-0.7.0.dist-info/top_level.txt
vents-0.7.0.dist-info/RECORD
